data_management/__init__.py
data_management/transform_data.py
three_functions_convert_data_learning_reason-1.0.0.dist-info/LICENSE
three_functions_convert_data_learning_reason-1.0.0.dist-info/METADATA
three_functions_convert_data_learning_reason-1.0.0.dist-info/WHEEL
three_functions_convert_data_learning_reason-1.0.0.dist-info/top_level.txt
three_functions_convert_data_learning_reason-1.0.0.dist-info/RECORD
