Metadata-Version: 2.1
Name: three-functions-convert-data-learning-reason
Version: 1.0.0
Summary: Three functions for learning to publish package in PyPi
Author-email: The great student <mail.not.work@mail.com>
License: The MIT License (MIT)
Project-URL: Homepage, https://github.com/TuringCollegeSubmissions/vipranc-DE2.1
Keywords: transpose2d,window1d,convolution2d
Classifier: License :: OSI Approved :: MIT License
Classifier: Programming Language :: Python
Classifier: Programming Language :: Python :: 3
Requires-Python: >=3.9
License-File: LICENSE
Requires-Dist: numpy (>=1.25.1)
Requires-Dist: tomli ; python_version < "3.11"
Provides-Extra: dev
Requires-Dist: black ; extra == 'dev'
Requires-Dist: bumpver ; extra == 'dev'
Requires-Dist: isort ; extra == 'dev'
Requires-Dist: pip-tools ; extra == 'dev'
Requires-Dist: pytest ; extra == 'dev'
